parallel_abus/__about__.py
parallel_abus/__init__.py
parallel_abus/aBUS_SuS/__init__.py
parallel_abus/aBUS_SuS/aBUS_SuS.py
parallel_abus/aBUS_SuS/aBUS_SuS_parallel.py
parallel_abus/aBUS_SuS/aCS_aBUS.py
parallel_abus/aBUS_SuS/aCS_aBUS_parallel.py
parallel_abus/aBUS_SuS/utils.py
parallel_abus/ERADistNataf/__init__.py
parallel_abus/ERADistNataf/ERACond.py
parallel_abus/ERADistNataf/ERADist.py
parallel_abus/ERADistNataf/ERANataf.py
parallel_abus/ERADistNataf/ERARosen.py
parallel_abus-0.2.1.dist-info/LICENSE.txt
parallel_abus-0.2.1.dist-info/METADATA
parallel_abus-0.2.1.dist-info/WHEEL
parallel_abus-0.2.1.dist-info/RECORD
