Metadata-Version: 2.1
Name: parallel-abus
Version: 0.2.1
Summary: 
License: MIT
Author:  Patrick Simon
Author-email: patrick.simon@bam.de
Requires-Python: >=3.10,<3.13
Classifier: Development Status :: 4 - Beta
Classifier: License :: OSI Approved :: MIT License
Classifier: Programming Language :: Python :: 3
Classifier: Programming Language :: Python :: 3.10
Classifier: Programming Language :: Python :: 3.11
Classifier: Programming Language :: Python :: 3.12
Classifier: Programming Language :: Python :: 3 :: Only
Classifier: Programming Language :: Python :: 3.8
Classifier: Programming Language :: Python :: 3.9
Classifier: Programming Language :: Python :: Implementation :: CPython
Classifier: Programming Language :: Python :: Implementation :: PyPy
Provides-Extra: networkx
Requires-Dist: networkx (>=3.0) ; extra == "networkx"
Requires-Dist: numpy (>=1.22)
Requires-Dist: scipy (>=1.6)
